nasa_wildfires/__init__.py
nasa_wildfires/cli.py
nasa_wildfires/options.py
nasa_wildfires-1.2.0.dist-info/LICENSE
nasa_wildfires-1.2.0.dist-info/METADATA
nasa_wildfires-1.2.0.dist-info/WHEEL
nasa_wildfires-1.2.0.dist-info/entry_points.txt
nasa_wildfires-1.2.0.dist-info/top_level.txt
nasa_wildfires-1.2.0.dist-info/RECORD
