Metadata-Version: 2.1
Name: nasa-wildfires
Version: 1.2.0
Summary: Download wildfire hotspots detected by NASA satellites and the Fire Information for Resource Management System (FIRMS)
Home-page: https://palewi.re/docs/nasa-wildfires/
Author: Ben Welsh
Author-email: b@palewi.re
License: MIT
Project-URL: Maintainer, https://github.com/datadesk
Project-URL: Source, https://github.com/datadesk/nasa-wildfires
Project-URL: Tracker, https://github.com/datadesk/nasa-wildfires/issues
Classifier: Development Status :: 5 - Production/Stable
Classifier: Programming Language :: Python
Classifier: Programming Language :: Python :: 3.8
Classifier: Programming Language :: Python :: 3.9
Classifier: Programming Language :: Python :: 3.10
Classifier: Programming Language :: Python :: 3.11
Classifier: Programming Language :: Python :: 3 :: Only
Classifier: License :: OSI Approved :: MIT License
License-File: LICENSE
Requires-Dist: requests
Requires-Dist: geojson
Requires-Dist: click
Requires-Dist: retry
